ibis_sqreamdb/__init__.py
ibis_sqreamdb/backend.py
ibis_sqreamdb/compiler.py
ibis_sqreamdb/datatypes.py
ibis_sqreamdb/dialect.py
ibis_sqreamdb/old_backend.py
ibis_sqreamdb-0.1.0.dist-info/METADATA
ibis_sqreamdb-0.1.0.dist-info/WHEEL
ibis_sqreamdb-0.1.0.dist-info/entry_points.txt
ibis_sqreamdb-0.1.0.dist-info/top_level.txt
ibis_sqreamdb-0.1.0.dist-info/RECORD
