Metadata-Version: 2.4
Name: ibis-sqreamdb
Version: 0.1.0
Summary: SQreamDB backend for the Ibis framework
License: Apache-2.0
Classifier: Development Status :: 3 - Alpha
Classifier: Programming Language :: Python
Classifier: Programming Language :: Python :: 3.9
Classifier: Programming Language :: Python :: 3.11
Classifier: Programming Language :: Python :: 3.12
Classifier: Intended Audience :: Developers
Classifier: Topic :: Software Development :: Libraries
Requires-Python: >=3.9
Requires-Dist: ibis-framework>=8.0.0
Requires-Dist: pysqream
Requires-Dist: sqlglot
Requires-Dist: pandas
